gpumonitor/__init__.py
gpumonitor/monitor.py
gpumonitor/callbacks/__init__.py
gpumonitor/callbacks/lightning.py
gpumonitor/callbacks/tf.py
gpumonitor-0.1.2.dist-info/LICENCE
gpumonitor-0.1.2.dist-info/METADATA
gpumonitor-0.1.2.dist-info/WHEEL
gpumonitor-0.1.2.dist-info/top_level.txt
gpumonitor-0.1.2.dist-info/RECORD
