Metadata-Version: 2.1
Name: gpumonitor
Version: 0.1.2
Summary: GPU Monitoring Callbacks for TensorFlow and PyTorch Lightning
Home-page: https://github.com/sicara/gpumonitor
Author: Raphael Meudec
Author-email: raphael.meudec@gmail.com
License: MIT
Platform: UNKNOWN
Classifier: Development Status :: 3 - Alpha
Classifier: License :: OSI Approved :: MIT License
Classifier: Programming Language :: Python
Classifier: Programming Language :: Python :: 3
Classifier: Programming Language :: Python :: 3.6
Classifier: Programming Language :: Python :: 3.7
Classifier: Operating System :: OS Independent
Requires-Python: >=3.6
Requires-Dist: gpustat (>=0.6.0)
Provides-Extra: publish
Requires-Dist: bumpversion (>=0.5.3) ; extra == 'publish'
Requires-Dist: twine (>=1.13.0) ; extra == 'publish'
